lepy-0.0.2.data/purelib/lepy/__init__.py
lepy-0.0.2.data/purelib/lepy/lepy.cp36-win_amd64.pyd
lepy-0.0.2.dist-info/LICENSE.txt
lepy-0.0.2.dist-info/METADATA
lepy-0.0.2.dist-info/WHEEL
lepy-0.0.2.dist-info/top_level.txt
lepy-0.0.2.dist-info/RECORD
